{
  "displayName": "Microsoft.CleanRoom",
  "id": "/providers/Microsoft.Authorization/providerOperations/Microsoft.CleanRoom",
  "name": "Microsoft.CleanRoom",
  "operations": [
    {
      "description": "Register the subscription for Microsoft.CleanRoom",
      "displayName": "Register the Microsoft.CleanRoom",
      "isDataAction": false,
      "name": "Microsoft.CleanRoom/register/action",
      "origin": null,
      "properties": null
    },
    {
      "description": "Unregister the subscription for Microsoft.CleanRoom",
      "displayName": "Unregister the Microsoft.CleanRoom",
      "isDataAction": false,
      "name": "Microsoft.CleanRoom/unregister/action",
      "origin": null,
      "properties": null
    }
  ],
  "resourceTypes": [
    {
      "displayName": "cleanrooms",
      "name": "cleanrooms",
      "operations": [
        {
          "description": "Get a clean room.",
          "displayName": "CleanRooms_Get",
          "isDataAction": false,
          "name": "Microsoft.CleanRoom/cleanrooms/read",
          "origin": null,
          "properties": null
        },
        {
          "description": "Create or update a clean room.",
          "displayName": "CleanRooms_Create",
          "isDataAction": false,
          "name": "Microsoft.CleanRoom/cleanrooms/write",
          "origin": null,
          "properties": null
        },
        {
          "description": "Deletes a clean room.",
          "displayName": "CleanRooms_Delete",
          "isDataAction": false,
          "name": "Microsoft.CleanRoom/cleanrooms/delete",
          "origin": null,
          "properties": null
        },
        {
          "description": "Update tags on a clean room.",
          "displayName": "CleanRooms_Update",
          "isDataAction": false,
          "name": "Microsoft.CleanRoom/cleanrooms/write",
          "origin": null,
          "properties": null
        },
        {
          "description": "List clean rooms in a subscription.",
          "displayName": "CleanRooms_ListBySubscription",
          "isDataAction": false,
          "name": "Microsoft.CleanRoom/cleanrooms/read",
          "origin": null,
          "properties": null
        },
        {
          "description": "List clean rooms in a resource group.",
          "displayName": "CleanRooms_ListByResourceGroup",
          "isDataAction": false,
          "name": "Microsoft.CleanRoom/cleanrooms/read",
          "origin": null,
          "properties": null
        }
      ]
    },
    {
      "displayName": "microservices",
      "name": "microservices",
      "operations": [
        {
          "description": "Get a micro service.",
          "displayName": "MicroServices_Get",
          "isDataAction": false,
          "name": "Microsoft.CleanRoom/microservices/read",
          "origin": null,
          "properties": null
        },
        {
          "description": "Create or update a micro service.",
          "displayName": "MicroServices_Create",
          "isDataAction": false,
          "name": "Microsoft.CleanRoom/microservices/write",
          "origin": null,
          "properties": null
        },
        {
          "description": "Deletes an micro service.",
          "displayName": "MicroServices_Delete",
          "isDataAction": false,
          "name": "Microsoft.CleanRoom/microservices/delete",
          "origin": null,
          "properties": null
        },
        {
          "description": "Updates tags on a micro service.",
          "displayName": "MicroServices_Update",
          "isDataAction": false,
          "name": "Microsoft.CleanRoom/microservices/write",
          "origin": null,
          "properties": null
        },
        {
          "description": "List micro services in a subscription.",
          "displayName": "MicroServices_ListBySubscription",
          "isDataAction": false,
          "name": "Microsoft.CleanRoom/microservices/read",
          "origin": null,
          "properties": null
        },
        {
          "description": "List micro services in a resource group.",
          "displayName": "MicroServices_ListByResourceGroup",
          "isDataAction": false,
          "name": "Microsoft.CleanRoom/microservices/read",
          "origin": null,
          "properties": null
        }
      ]
    },
    {
      "displayName": "Operations",
      "name": "Operations",
      "operations": [
        {
          "description": "read Operations",
          "displayName": "read_Operations",
          "isDataAction": false,
          "name": "Microsoft.CleanRoom/Operations/read",
          "origin": null,
          "properties": null
        }
      ]
    },
    {
      "displayName": "Locations/OperationStatuses",
      "name": "Locations/OperationStatuses",
      "operations": [
        {
          "description": "read OperationStatuses",
          "displayName": "read_OperationStatuses",
          "isDataAction": false,
          "name": "Microsoft.CleanRoom/Locations/OperationStatuses/read",
          "origin": null,
          "properties": null
        },
        {
          "description": "write OperationStatuses",
          "displayName": "write_OperationStatuses",
          "isDataAction": false,
          "name": "Microsoft.CleanRoom/Locations/OperationStatuses/write",
          "origin": null,
          "properties": null
        }
      ]
    }
  ],
  "type": "Microsoft.Authorization/providerOperations"
}
