{
  "displayName": "Microsoft.DesktopVirtualization",
  "id": "/providers/Microsoft.Authorization/providerOperations/Microsoft.DesktopVirtualization",
  "name": "Microsoft.DesktopVirtualization",
  "operations": [
    {
      "description": "Action on unregister",
      "displayName": "unregister",
      "isDataAction": false,
      "name": "Microsoft.DesktopVirtualization/unregister/action",
      "origin": null,
      "properties": null
    },
    {
      "description": "Register subscription",
      "displayName": "register",
      "isDataAction": false,
      "name": "Microsoft.DesktopVirtualization/register/action",
      "origin": null,
      "properties": null
    }
  ],
  "resourceTypes": [
    {
      "displayName": "workspaces",
      "name": "workspaces",
      "operations": [
        {
          "description": "Read workspaces",
          "displayName": "Read workspaces",
          "isDataAction": false,
          "name": "Microsoft.DesktopVirtualization/workspaces/read",
          "origin": null,
          "properties": null
        },
        {
          "description": "Write workspaces",
          "displayName": "Write workspaces",
          "isDataAction": false,
          "name": "Microsoft.DesktopVirtualization/workspaces/write",
          "origin": null,
          "properties": null
        },
        {
          "description": "Delete workspaces",
          "displayName": "Delete workspaces",
          "isDataAction": false,
          "name": "Microsoft.DesktopVirtualization/workspaces/delete",
          "origin": null,
          "properties": null
        },
        {
          "description": "Move a workspaces to another resource group",
          "displayName": "Move workspaces",
          "isDataAction": false,
          "name": "Microsoft.DesktopVirtualization/workspaces/move/action",
          "origin": null,
          "properties": null
        }
      ]
    },
    {
      "displayName": "applicationgroups",
      "name": "applicationgroups",
      "operations": [
        {
          "description": "Read applicationgroups",
          "displayName": "Read applicationgroups",
          "isDataAction": false,
          "name": "Microsoft.DesktopVirtualization/applicationgroups/read",
          "origin": null,
          "properties": null
        },
        {
          "description": "Write applicationgroups",
          "displayName": "Write applicationgroups",
          "isDataAction": false,
          "name": "Microsoft.DesktopVirtualization/applicationgroups/write",
          "origin": null,
          "properties": null
        },
        {
          "description": "Delete applicationgroups",
          "displayName": "Delete applicationgroups",
          "isDataAction": false,
          "name": "Microsoft.DesktopVirtualization/applicationgroups/delete",
          "origin": null,
          "properties": null
        },
        {
          "description": "Use ApplicationGroup",
          "displayName": "Use ApplicationGroup",
          "isDataAction": true,
          "name": "Microsoft.DesktopVirtualization/applicationgroups/useapplications/action",
          "origin": null,
          "properties": null
        },
        {
          "description": "Move a applicationgroups to another resource group",
          "displayName": "Move applicationgroups",
          "isDataAction": false,
          "name": "Microsoft.DesktopVirtualization/applicationgroups/move/action",
          "origin": null,
          "properties": null
        }
      ]
    },
    {
      "displayName": "applicationgroups/applications",
      "name": "applicationgroups/applications",
      "operations": [
        {
          "description": "Read applicationgroups/applications",
          "displayName": "Read applicationgroups/applications",
          "isDataAction": false,
          "name": "Microsoft.DesktopVirtualization/applicationgroups/applications/read",
          "origin": null,
          "properties": null
        },
        {
          "description": "Write applicationgroups/applications",
          "displayName": "Write applicationgroups/applications",
          "isDataAction": false,
          "name": "Microsoft.DesktopVirtualization/applicationgroups/applications/write",
          "origin": null,
          "properties": null
        },
        {
          "description": "Delete applicationgroups/applications",
          "displayName": "Delete applicationgroups/applications",
          "isDataAction": false,
          "name": "Microsoft.DesktopVirtualization/applicationgroups/applications/delete",
          "origin": null,
          "properties": null
        }
      ]
    },
    {
      "displayName": "applicationgroups/startmenuitems",
      "name": "applicationgroups/startmenuitems",
      "operations": [
        {
          "description": "Read start menu items",
          "displayName": "startmenuitems",
          "isDataAction": false,
          "name": "Microsoft.DesktopVirtualization/applicationgroups/startmenuitems/read",
          "origin": null,
          "properties": null
        }
      ]
    },
    {
      "displayName": "hostpools",
      "name": "hostpools",
      "operations": [
        {
          "description": "Read hostpools",
          "displayName": "Read hostpools",
          "isDataAction": false,
          "name": "Microsoft.DesktopVirtualization/hostpools/read",
          "origin": null,
          "properties": null
        },
        {
          "description": "Write hostpools",
          "displayName": "Write hostpools",
          "isDataAction": false,
          "name": "Microsoft.DesktopVirtualization/hostpools/write",
          "origin": null,
          "properties": null
        },
        {
          "description": "Delete hostpools",
          "displayName": "Delete hostpools",
          "isDataAction": false,
          "name": "Microsoft.DesktopVirtualization/hostpools/delete",
          "origin": null,
          "properties": null
        },
        {
          "description": null,
          "displayName": null,
          "isDataAction": false,
          "name": "Microsoft.DesktopVirtualization/hostpools/controlUpdate/action",
          "origin": null,
          "properties": null
        },
        {
          "description": "Action on update",
          "displayName": "update",
          "isDataAction": false,
          "name": "Microsoft.DesktopVirtualization/hostpools/update/action",
          "origin": null,
          "properties": null
        },
        {
          "description": "Retrieve registration token for host pool",
          "displayName": "retrieveRegistrationToken",
          "isDataAction": false,
          "name": "Microsoft.DesktopVirtualization/hostpools/retrieveRegistrationToken/action",
          "origin": null,
          "properties": null
        },
        {
          "description": "Move a hostpools to another resource group",
          "displayName": "Move hostpools",
          "isDataAction": false,
          "name": "Microsoft.DesktopVirtualization/hostpools/move/action",
          "origin": null,
          "properties": null
        },
        {
          "description": "Expand an expandmsiximage to see MSIX Packages present",
          "displayName": "Expand expandmsiximage",
          "isDataAction": false,
          "name": "Microsoft.DesktopVirtualization/hostpools/expandmsiximage/action",
          "origin": null,
          "properties": null
        }
      ]
    },
    {
      "displayName": "hostpools",
      "name": "hostpools/providers/Microsoft.Insights/logDefinitions",
      "operations": [
        {
          "description": "Gets the available logs",
          "displayName": "Read log definitions",
          "isDataAction": false,
          "name": "Microsoft.DesktopVirtualization/hostpools/providers/Microsoft.Insights/logDefinitions/read",
          "origin": null,
          "properties": {
            "serviceSpecification": {
              "logSpecifications": [
                {
                  "displayName": "Checkpoint",
                  "name": "Checkpoint"
                },
                {
                  "displayName": "Error",
                  "name": "Error"
                },
                {
                  "displayName": "Management",
                  "name": "Management"
                },
                {
                  "displayName": "Connection",
                  "name": "Connection"
                },
                {
                  "displayName": "HostRegistration",
                  "name": "HostRegistration"
                },
                {
                  "displayName": "AgentHealthStatus",
                  "name": "AgentHealthStatus"
                }
              ]
            }
          }
        }
      ]
    },
    {
      "displayName": "hostpools",
      "name": "hostpools/providers/Microsoft.Insights/diagnosticSettings",
      "operations": [
        {
          "description": "Gets the diagnostic setting",
          "displayName": "Get diagnostic setting",
          "isDataAction": false,
          "name": "Microsoft.DesktopVirtualization/hostpools/providers/Microsoft.Insights/diagnosticSettings/read",
          "origin": null,
          "properties": null
        },
        {
          "description": "Creates or updates the diagnostic setting",
          "displayName": "Create or update the diagnostic setting",
          "isDataAction": false,
          "name": "Microsoft.DesktopVirtualization/hostpools/providers/Microsoft.Insights/diagnosticSettings/write",
          "origin": null,
          "properties": null
        }
      ]
    },
    {
      "displayName": "hostpools/sessionhosts",
      "name": "hostpools/sessionhosts",
      "operations": [
        {
          "description": "Read hostpools/sessionhosts",
          "displayName": "Read hostpools/sessionhosts",
          "isDataAction": false,
          "name": "Microsoft.DesktopVirtualization/hostpools/sessionhosts/read",
          "origin": null,
          "properties": null
        },
        {
          "description": "Write hostpools/sessionhosts",
          "displayName": "Write hostpools/sessionhosts",
          "isDataAction": false,
          "name": "Microsoft.DesktopVirtualization/hostpools/sessionhosts/write",
          "origin": null,
          "properties": null
        },
        {
          "description": "Delete hostpools/sessionhosts",
          "displayName": "Delete hostpools/sessionhosts",
          "isDataAction": false,
          "name": "Microsoft.DesktopVirtualization/hostpools/sessionhosts/delete",
          "origin": null,
          "properties": null
        }
      ]
    },
    {
      "displayName": "hostpools/sessionhosts/usersessions",
      "name": "hostpools/sessionhosts/usersessions",
      "operations": [
        {
          "description": "Read hostpools/sessionhosts/usersessions",
          "displayName": "Read hostpools/sessionhosts/usersessions",
          "isDataAction": false,
          "name": "Microsoft.DesktopVirtualization/hostpools/sessionhosts/usersessions/read",
          "origin": null,
          "properties": null
        },
        {
          "description": "Write hostpools/sessionhosts/usersessions",
          "displayName": "Write hostpools/sessionhosts/usersessions",
          "isDataAction": false,
          "name": "Microsoft.DesktopVirtualization/hostpools/sessionhosts/usersessions/write",
          "origin": null,
          "properties": null
        },
        {
          "description": "Delete hostpools/sessionhosts/usersessions",
          "displayName": "Delete hostpools/sessionhosts/usersessions",
          "isDataAction": false,
          "name": "Microsoft.DesktopVirtualization/hostpools/sessionhosts/usersessions/delete",
          "origin": null,
          "properties": null
        },
        {
          "description": "Disconnects the user session form session host",
          "displayName": "disconnect",
          "isDataAction": false,
          "name": "Microsoft.DesktopVirtualization/hostpools/sessionhosts/usersessions/disconnect/action",
          "origin": null,
          "properties": null
        },
        {
          "description": "Send message to user session",
          "displayName": "sendMessage",
          "isDataAction": false,
          "name": "Microsoft.DesktopVirtualization/hostpools/sessionhosts/usersessions/sendMessage/action",
          "origin": null,
          "properties": null
        }
      ]
    },
    {
      "displayName": "workspaces",
      "name": "workspaces/providers/Microsoft.Insights/logDefinitions",
      "operations": [
        {
          "description": "Gets the available logs",
          "displayName": "Read log definitions",
          "isDataAction": false,
          "name": "Microsoft.DesktopVirtualization/workspaces/providers/Microsoft.Insights/logDefinitions/read",
          "origin": null,
          "properties": {
            "serviceSpecification": {
              "logSpecifications": [
                {
                  "displayName": "Checkpoint",
                  "name": "Checkpoint"
                },
                {
                  "displayName": "Error",
                  "name": "Error"
                },
                {
                  "displayName": "Management",
                  "name": "Management"
                },
                {
                  "displayName": "Feed",
                  "name": "Feed"
                }
              ]
            }
          }
        }
      ]
    },
    {
      "displayName": "workspaces",
      "name": "workspaces/providers/Microsoft.Insights/diagnosticSettings",
      "operations": [
        {
          "description": "Gets the diagnostic setting",
          "displayName": "Get diagnostic setting",
          "isDataAction": false,
          "name": "Microsoft.DesktopVirtualization/workspaces/providers/Microsoft.Insights/diagnosticSettings/read",
          "origin": null,
          "properties": null
        },
        {
          "description": "Creates or updates the diagnostic setting",
          "displayName": "Create or update the diagnostic setting",
          "isDataAction": false,
          "name": "Microsoft.DesktopVirtualization/workspaces/providers/Microsoft.Insights/diagnosticSettings/write",
          "origin": null,
          "properties": null
        }
      ]
    },
    {
      "displayName": "applicationgroups",
      "name": "applicationgroups/providers/Microsoft.Insights/logDefinitions",
      "operations": [
        {
          "description": "Gets the available logs",
          "displayName": "Read log definitions",
          "isDataAction": false,
          "name": "Microsoft.DesktopVirtualization/applicationgroups/providers/Microsoft.Insights/logDefinitions/read",
          "origin": null,
          "properties": {
            "serviceSpecification": {
              "logSpecifications": [
                {
                  "displayName": "Checkpoint",
                  "name": "Checkpoint"
                },
                {
                  "displayName": "Error",
                  "name": "Error"
                },
                {
                  "displayName": "Management",
                  "name": "Management"
                }
              ]
            }
          }
        }
      ]
    },
    {
      "displayName": "applicationgroups",
      "name": "applicationgroups/providers/Microsoft.Insights/diagnosticSettings",
      "operations": [
        {
          "description": "Gets the diagnostic setting",
          "displayName": "Get diagnostic setting",
          "isDataAction": false,
          "name": "Microsoft.DesktopVirtualization/applicationgroups/providers/Microsoft.Insights/diagnosticSettings/read",
          "origin": null,
          "properties": null
        },
        {
          "description": "Creates or updates the diagnostic setting",
          "displayName": "Create or update the diagnostic setting",
          "isDataAction": false,
          "name": "Microsoft.DesktopVirtualization/applicationgroups/providers/Microsoft.Insights/diagnosticSettings/write",
          "origin": null,
          "properties": null
        }
      ]
    },
    {
      "displayName": "applicationgroups/desktops",
      "name": "applicationgroups/desktops",
      "operations": [
        {
          "description": "Read applicationgroups/desktops",
          "displayName": "Read applicationgroups/desktops",
          "isDataAction": false,
          "name": "Microsoft.DesktopVirtualization/applicationgroups/desktops/read",
          "origin": null,
          "properties": null
        },
        {
          "description": "Write applicationgroups/desktops",
          "displayName": "Write applicationgroups/desktops",
          "isDataAction": false,
          "name": "Microsoft.DesktopVirtualization/applicationgroups/desktops/write",
          "origin": null,
          "properties": null
        },
        {
          "description": "Delete applicationgroups/desktops",
          "displayName": "Delete applicationgroups/desktops",
          "isDataAction": false,
          "name": "Microsoft.DesktopVirtualization/applicationgroups/desktops/delete",
          "origin": null,
          "properties": null
        }
      ]
    },
    {
      "displayName": "applicationgroups/externaluserassignments",
      "name": "applicationgroups/externaluserassignments",
      "operations": [
        {
          "description": null,
          "displayName": null,
          "isDataAction": false,
          "name": "Microsoft.DesktopVirtualization/applicationgroups/externaluserassignments/read",
          "origin": null,
          "properties": null
        },
        {
          "description": null,
          "displayName": null,
          "isDataAction": false,
          "name": "Microsoft.DesktopVirtualization/applicationgroups/externaluserassignments/write",
          "origin": null,
          "properties": null
        }
      ]
    },
    {
      "displayName": "hostpools/privateendpointconnectionproxies",
      "name": "hostpools/privateendpointconnectionproxies",
      "operations": [
        {
          "description": "Read hostpools/privateendpointconnectionproxies",
          "displayName": "Read hostpools/privateendpointconnectionproxies",
          "isDataAction": false,
          "name": "Microsoft.DesktopVirtualization/hostpools/privateendpointconnectionproxies/read",
          "origin": null,
          "properties": null
        },
        {
          "description": "Write hostpools/privateendpointconnectionproxies",
          "displayName": "Write hostpools/privateendpointconnectionproxies",
          "isDataAction": false,
          "name": "Microsoft.DesktopVirtualization/hostpools/privateendpointconnectionproxies/write",
          "origin": null,
          "properties": null
        },
        {
          "description": "Delete hostpools/privateendpointconnectionproxies",
          "displayName": "Delete hostpools/privateendpointconnectionproxies",
          "isDataAction": false,
          "name": "Microsoft.DesktopVirtualization/hostpools/privateendpointconnectionproxies/delete",
          "origin": null,
          "properties": null
        },
        {
          "description": "Validates the private endpoint connection proxy",
          "displayName": "validate",
          "isDataAction": false,
          "name": "Microsoft.DesktopVirtualization/hostpools/privateendpointconnectionproxies/validate/action",
          "origin": null,
          "properties": null
        }
      ]
    },
    {
      "displayName": "hostpools/privateendpointconnectionproxies/operationresults",
      "name": "hostpools/privateendpointconnectionproxies/operationresults",
      "operations": [
        {
          "description": "Gets operation result on private endpoint connection proxy",
          "displayName": "operationresults",
          "isDataAction": false,
          "name": "Microsoft.DesktopVirtualization/hostpools/privateendpointconnectionproxies/operationresults/read",
          "origin": null,
          "properties": null
        }
      ]
    },
    {
      "displayName": "workspaces/privateendpointconnectionproxies",
      "name": "workspaces/privateendpointconnectionproxies",
      "operations": [
        {
          "description": "Read workspaces/privateendpointconnectionproxies",
          "displayName": "Read workspaces/privateendpointconnectionproxies",
          "isDataAction": false,
          "name": "Microsoft.DesktopVirtualization/workspaces/privateendpointconnectionproxies/read",
          "origin": null,
          "properties": null
        },
        {
          "description": "Write workspaces/privateendpointconnectionproxies",
          "displayName": "Write workspaces/privateendpointconnectionproxies",
          "isDataAction": false,
          "name": "Microsoft.DesktopVirtualization/workspaces/privateendpointconnectionproxies/write",
          "origin": null,
          "properties": null
        },
        {
          "description": "Delete workspaces/privateendpointconnectionproxies",
          "displayName": "Delete workspaces/privateendpointconnectionproxies",
          "isDataAction": false,
          "name": "Microsoft.DesktopVirtualization/workspaces/privateendpointconnectionproxies/delete",
          "origin": null,
          "properties": null
        },
        {
          "description": "Validates the private endpoint connection proxy",
          "displayName": "validate",
          "isDataAction": false,
          "name": "Microsoft.DesktopVirtualization/workspaces/privateendpointconnectionproxies/validate/action",
          "origin": null,
          "properties": null
        }
      ]
    },
    {
      "displayName": "workspaces/privateendpointconnectionproxies/operationresults",
      "name": "workspaces/privateendpointconnectionproxies/operationresults",
      "operations": [
        {
          "description": "Gets operation result on private endpoint connection proxy",
          "displayName": "operationresults",
          "isDataAction": false,
          "name": "Microsoft.DesktopVirtualization/workspaces/privateendpointconnectionproxies/operationresults/read",
          "origin": null,
          "properties": null
        }
      ]
    },
    {
      "displayName": "hostpools/sessionhostconfigurations",
      "name": "hostpools/sessionhostconfigurations",
      "operations": [
        {
          "description": "Read hostpools/sessionhostconfigurations",
          "displayName": "Read hostpools/sessionhostconfigurations",
          "isDataAction": false,
          "name": "Microsoft.DesktopVirtualization/hostpools/sessionhostconfigurations/read",
          "origin": null,
          "properties": null
        },
        {
          "description": "Write hostpools/sessionhostconfigurations",
          "displayName": "Write hostpools/sessionhostconfigurations",
          "isDataAction": false,
          "name": "Microsoft.DesktopVirtualization/hostpools/sessionhostconfigurations/write",
          "origin": null,
          "properties": null
        },
        {
          "description": "Delete hostpools/sessionhostconfigurations",
          "displayName": "Delete hostpools/sessionhostconfigurations",
          "isDataAction": false,
          "name": "Microsoft.DesktopVirtualization/hostpools/sessionhostconfigurations/delete",
          "origin": null,
          "properties": null
        }
      ]
    },
    {
      "displayName": "hostpools/msixpackages",
      "name": "hostpools/msixpackages",
      "operations": [
        {
          "description": "Read hostpools/msixpackages",
          "displayName": "Read hostpools/msixpackages",
          "isDataAction": false,
          "name": "Microsoft.DesktopVirtualization/hostpools/msixpackages/read",
          "origin": null,
          "properties": null
        },
        {
          "description": "Write hostpools/msixpackages",
          "displayName": "Write hostpools/msixpackages",
          "isDataAction": false,
          "name": "Microsoft.DesktopVirtualization/hostpools/msixpackages/write",
          "origin": null,
          "properties": null
        },
        {
          "description": "Delete hostpools/msixpackages",
          "displayName": "Delete hostpools/msixpackages",
          "isDataAction": false,
          "name": "Microsoft.DesktopVirtualization/hostpools/msixpackages/delete",
          "origin": null,
          "properties": null
        }
      ]
    },
    {
      "displayName": "scalingplans",
      "name": "scalingplans",
      "operations": [
        {
          "description": "Read scalingplans",
          "displayName": "Read scalingplans",
          "isDataAction": false,
          "name": "Microsoft.DesktopVirtualization/scalingplans/read",
          "origin": null,
          "properties": null
        },
        {
          "description": "Write scalingplans",
          "displayName": "Write scalingplans",
          "isDataAction": false,
          "name": "Microsoft.DesktopVirtualization/scalingplans/write",
          "origin": null,
          "properties": null
        },
        {
          "description": "Delete scalingplans",
          "displayName": "Delete scalingplans",
          "isDataAction": false,
          "name": "Microsoft.DesktopVirtualization/scalingplans/delete",
          "origin": null,
          "properties": null
        },
        {
          "description": "Move scalingplans to another ResourceGroup or Subscription",
          "displayName": "Move scalingplans",
          "isDataAction": false,
          "name": "Microsoft.DesktopVirtualization/scalingplans/move/action",
          "origin": null,
          "properties": null
        }
      ]
    },
    {
      "displayName": "scalingplans/pooledSchedules",
      "name": "scalingplans/pooledSchedules",
      "operations": [
        {
          "description": "Read scalingplans/pooledSchedules",
          "displayName": "Read scalingplans/pooledSchedules",
          "isDataAction": false,
          "name": "Microsoft.DesktopVirtualization/scalingplans/pooledSchedules/read",
          "origin": null,
          "properties": null
        },
        {
          "description": "Write scalingplans/pooledSchedules",
          "displayName": "Write scalingplans/pooledSchedules",
          "isDataAction": false,
          "name": "Microsoft.DesktopVirtualization/scalingplans/pooledSchedules/write",
          "origin": null,
          "properties": null
        },
        {
          "description": "Delete scalingplans/pooledSchedules",
          "displayName": "Delete scalingplans/pooledSchedules",
          "isDataAction": false,
          "name": "Microsoft.DesktopVirtualization/scalingplans/pooledSchedules/delete",
          "origin": null,
          "properties": null
        }
      ]
    },
    {
      "displayName": "scalingplans/personalSchedules",
      "name": "scalingplans/personalSchedules",
      "operations": [
        {
          "description": "Read scalingplans/personalSchedules",
          "displayName": "Read scalingplans/personalSchedules",
          "isDataAction": false,
          "name": "Microsoft.DesktopVirtualization/scalingplans/personalSchedules/read",
          "origin": null,
          "properties": null
        },
        {
          "description": "Write scalingplans/personalSchedules",
          "displayName": "Write scalingplans/personalSchedules",
          "isDataAction": false,
          "name": "Microsoft.DesktopVirtualization/scalingplans/personalSchedules/write",
          "origin": null,
          "properties": null
        },
        {
          "description": "Delete scalingplans/personalSchedules",
          "displayName": "Delete scalingplans/personalSchedules",
          "isDataAction": false,
          "name": "Microsoft.DesktopVirtualization/scalingplans/personalSchedules/delete",
          "origin": null,
          "properties": null
        }
      ]
    },
    {
      "displayName": "hostpools/scalingplans",
      "name": "hostpools/scalingplans",
      "operations": [
        {
          "description": "Read scalingplans",
          "displayName": "scalingplans",
          "isDataAction": false,
          "name": "Microsoft.DesktopVirtualization/hostpools/scalingplans/read",
          "origin": null,
          "properties": null
        }
      ]
    },
    {
      "displayName": "hostpools/updateDetails",
      "name": "hostpools/updateDetails",
      "operations": [
        {
          "description": "Read updateDetails",
          "displayName": "updateDetails",
          "isDataAction": false,
          "name": "Microsoft.DesktopVirtualization/hostpools/updateDetails/read",
          "origin": null,
          "properties": null
        }
      ]
    },
    {
      "displayName": "hostpools/updateOperationResults",
      "name": "hostpools/updateOperationResults",
      "operations": [
        {
          "description": "Read updateOperationResults",
          "displayName": "updateOperationResults",
          "isDataAction": false,
          "name": "Microsoft.DesktopVirtualization/hostpools/updateOperationResults/read",
          "origin": null,
          "properties": null
        }
      ]
    },
    {
      "displayName": "hostpools/privateendpointconnections",
      "name": "hostpools/privateendpointconnections",
      "operations": [
        {
          "description": "Read hostpools/privateendpointconnections",
          "displayName": "Read hostpools/privateendpointconnections",
          "isDataAction": false,
          "name": "Microsoft.DesktopVirtualization/hostpools/privateendpointconnections/read",
          "origin": null,
          "properties": null
        },
        {
          "description": "Write hostpools/privateendpointconnections",
          "displayName": "Write hostpools/privateendpointconnections",
          "isDataAction": false,
          "name": "Microsoft.DesktopVirtualization/hostpools/privateendpointconnections/write",
          "origin": null,
          "properties": null
        },
        {
          "description": "Delete hostpools/privateendpointconnections",
          "displayName": "Delete hostpools/privateendpointconnections",
          "isDataAction": false,
          "name": "Microsoft.DesktopVirtualization/hostpools/privateendpointconnections/delete",
          "origin": null,
          "properties": null
        }
      ]
    },
    {
      "displayName": "workspaces/privateendpointconnections",
      "name": "workspaces/privateendpointconnections",
      "operations": [
        {
          "description": "Read workspaces/privateendpointconnections",
          "displayName": "Read workspaces/privateendpointconnections",
          "isDataAction": false,
          "name": "Microsoft.DesktopVirtualization/workspaces/privateendpointconnections/read",
          "origin": null,
          "properties": null
        },
        {
          "description": "Write workspaces/privateendpointconnections",
          "displayName": "Write workspaces/privateendpointconnections",
          "isDataAction": false,
          "name": "Microsoft.DesktopVirtualization/workspaces/privateendpointconnections/write",
          "origin": null,
          "properties": null
        },
        {
          "description": "Delete workspaces/privateendpointconnections",
          "displayName": "Delete workspaces/privateendpointconnections",
          "isDataAction": false,
          "name": "Microsoft.DesktopVirtualization/workspaces/privateendpointconnections/delete",
          "origin": null,
          "properties": null
        }
      ]
    },
    {
      "displayName": "hostpools/privatelinkresources",
      "name": "hostpools/privatelinkresources",
      "operations": [
        {
          "description": "Read privatelinkresources",
          "displayName": "privatelinkresources",
          "isDataAction": false,
          "name": "Microsoft.DesktopVirtualization/hostpools/privatelinkresources/read",
          "origin": null,
          "properties": null
        }
      ]
    },
    {
      "displayName": "workspaces/privatelinkresources",
      "name": "workspaces/privatelinkresources",
      "operations": [
        {
          "description": "Read privatelinkresources",
          "displayName": "privatelinkresources",
          "isDataAction": false,
          "name": "Microsoft.DesktopVirtualization/workspaces/privatelinkresources/read",
          "origin": null,
          "properties": null
        }
      ]
    },
    {
      "displayName": "hostpools/usersessions",
      "name": "hostpools/usersessions",
      "operations": [
        {
          "description": "Read usersessions",
          "displayName": "usersessions",
          "isDataAction": false,
          "name": "Microsoft.DesktopVirtualization/hostpools/usersessions/read",
          "origin": null,
          "properties": null
        }
      ]
    },
    {
      "displayName": "operations",
      "name": "operations",
      "operations": [
        {
          "description": "Read operations",
          "displayName": "operations",
          "isDataAction": false,
          "name": "Microsoft.DesktopVirtualization/operations/read",
          "origin": null,
          "properties": null
        }
      ]
    },
    {
      "displayName": "resourceTypes",
      "name": "resourceTypes",
      "operations": [
        {
          "description": "Read resourceTypes",
          "displayName": "resourceTypes",
          "isDataAction": false,
          "name": "Microsoft.DesktopVirtualization/resourceTypes/read",
          "origin": null,
          "properties": null
        }
      ]
    }
  ],
  "type": "Microsoft.Authorization/providerOperations"
}
