{
  "displayName": "Microsoft.AzureStackHCI",
  "id": "/providers/Microsoft.Authorization/providerOperations/Microsoft.AzureStackHCI",
  "name": "Microsoft.AzureStackHCI",
  "operations": [
    {
      "description": "Registers the subscription for the Azure Stack HCI resource provider and enables the creation of Azure Stack HCI resources.",
      "displayName": "Registers the Azure Stack HCI Resource Provider",
      "isDataAction": false,
      "name": "Microsoft.AzureStackHCI/Register/Action",
      "origin": "System",
      "properties": null
    },
    {
      "description": "Unregisters the subscription for the Azure Stack HCI resource provider.",
      "displayName": "Unregisters the Azure Stack HCI Resource Provider",
      "isDataAction": false,
      "name": "Microsoft.AzureStackHCI/Unregister/Action",
      "origin": "System",
      "properties": null
    }
  ],
  "resourceTypes": [
    {
      "displayName": "Clusters",
      "name": "Clusters",
      "operations": [
        {
          "description": "Gets clusters",
          "displayName": "Gets/List cluster resources",
          "isDataAction": false,
          "name": "Microsoft.AzureStackHCI/Clusters/Read",
          "origin": "System",
          "properties": null
        },
        {
          "description": "Creates or updates a cluster",
          "displayName": "Create/update cluster resources",
          "isDataAction": false,
          "name": "Microsoft.AzureStackHCI/Clusters/Write",
          "origin": null,
          "properties": null
        },
        {
          "description": "Deletes cluster resource",
          "displayName": "Deletes cluster resource",
          "isDataAction": false,
          "name": "Microsoft.AzureStackHCI/Clusters/Delete",
          "origin": null,
          "properties": null
        },
        {
          "description": "Create cluster identity",
          "displayName": "Create cluster identity",
          "isDataAction": false,
          "name": "Microsoft.AzureStackHCI/Clusters/CreateClusterIdentity/Action",
          "origin": null,
          "properties": null
        },
        {
          "description": "Upload cluster certificate",
          "displayName": "Upload cluster certificate",
          "isDataAction": false,
          "name": "Microsoft.AzureStackHCI/Clusters/UploadCertificate/Action",
          "origin": null,
          "properties": null
        },
        {
          "description": "Manage OS of HCI resource via Windows Admin Center as an administrator",
          "displayName": "Manage OS of HCI resource via Windows Admin Center as an administrator",
          "isDataAction": true,
          "name": "Microsoft.AzureStackHCI/Clusters/WACloginAsAdmin/Action",
          "origin": null,
          "properties": null
        }
      ]
    },
    {
      "displayName": "Operations",
      "name": "Operations",
      "operations": [
        {
          "description": "Gets operations",
          "displayName": "Gets/List operations resources",
          "isDataAction": false,
          "name": "Microsoft.AzureStackHCI/Operations/Read",
          "origin": "System",
          "properties": null
        }
      ]
    },
    {
      "displayName": "Clusters/ArcSettings",
      "name": "Clusters/ArcSettings",
      "operations": [
        {
          "description": "Gets arc resource of HCI cluster",
          "displayName": "Gets/List arc resources",
          "isDataAction": false,
          "name": "Microsoft.AzureStackHCI/Clusters/ArcSettings/Read",
          "origin": null,
          "properties": null
        },
        {
          "description": "Create or updates arc resource of HCI cluster",
          "displayName": "Create/Update arc resources",
          "isDataAction": false,
          "name": "Microsoft.AzureStackHCI/Clusters/ArcSettings/Write",
          "origin": null,
          "properties": null
        },
        {
          "description": "Delete arc resource of HCI cluster",
          "displayName": "Delete arc resources",
          "isDataAction": false,
          "name": "Microsoft.AzureStackHCI/Clusters/ArcSettings/Delete",
          "origin": null,
          "properties": null
        },
        {
          "description": "Generate password for Arc settings identity",
          "displayName": "Generate password for Arc settings identity",
          "isDataAction": false,
          "name": "Microsoft.AzureStackHCI/Clusters/ArcSettings/GeneratePassword/Action",
          "origin": null,
          "properties": null
        },
        {
          "description": "Create Arc settings identity",
          "displayName": "Create Arc settings identity",
          "isDataAction": false,
          "name": "Microsoft.AzureStackHCI/Clusters/ArcSettings/CreateArcIdentity/Action",
          "origin": null,
          "properties": null
        }
      ]
    },
    {
      "displayName": "Clusters/ArcSettings/Extensions",
      "name": "Clusters/ArcSettings/Extensions",
      "operations": [
        {
          "description": "Gets extension resource of HCI cluster",
          "displayName": "Gets/List extension resources of HCI cluster",
          "isDataAction": false,
          "name": "Microsoft.AzureStackHCI/Clusters/ArcSettings/Extensions/Read",
          "origin": null,
          "properties": null
        },
        {
          "description": "Create or update extension resource of HCI cluster",
          "displayName": "Create/Update extension resources of HCI cluster",
          "isDataAction": false,
          "name": "Microsoft.AzureStackHCI/Clusters/ArcSettings/Extensions/Write",
          "origin": null,
          "properties": null
        },
        {
          "description": "Delete extension resources of HCI cluster",
          "displayName": "Delete extension resources of HCI cluster",
          "isDataAction": false,
          "name": "Microsoft.AzureStackHCI/Clusters/ArcSettings/Extensions/Delete",
          "origin": null,
          "properties": null
        },
        {
          "description": "Upgrade extension resources of HCI cluster",
          "displayName": "Upgrade extension resources of HCI cluster",
          "isDataAction": false,
          "name": "Microsoft.AzureStackHCI/Clusters/ArcSettings/Extensions/Upgrade/Action",
          "origin": null,
          "properties": null
        }
      ]
    },
    {
      "displayName": "VirtualMachines",
      "name": "VirtualMachines",
      "operations": [
        {
          "description": "Restarts virtual machine resource",
          "displayName": "Restarts virtual machine resource",
          "isDataAction": false,
          "name": "Microsoft.AzureStackHCI/VirtualMachines/Restart/Action",
          "origin": null,
          "properties": null
        },
        {
          "description": "Starts virtual machine resource",
          "displayName": "Starts virtual machine resource",
          "isDataAction": false,
          "name": "Microsoft.AzureStackHCI/VirtualMachines/Start/Action",
          "origin": null,
          "properties": null
        },
        {
          "description": "Stops virtual machine resource",
          "displayName": "Stops virtual machine resource",
          "isDataAction": false,
          "name": "Microsoft.AzureStackHCI/VirtualMachines/Stop/Action",
          "origin": null,
          "properties": null
        },
        {
          "description": "Deletes virtual machine resource",
          "displayName": "Deletes virtual machine resource",
          "isDataAction": false,
          "name": "Microsoft.AzureStackHCI/VirtualMachines/Delete",
          "origin": null,
          "properties": null
        },
        {
          "description": "Creates/Updates virtual machine resource",
          "displayName": "Creates/Updates virtual machine resource",
          "isDataAction": false,
          "name": "Microsoft.AzureStackHCI/VirtualMachines/Write",
          "origin": null,
          "properties": null
        },
        {
          "description": "Gets/Lists virtual machine resource",
          "displayName": "Gets/Lists virtual machine resource",
          "isDataAction": false,
          "name": "Microsoft.AzureStackHCI/VirtualMachines/Read",
          "origin": null,
          "properties": null
        }
      ]
    },
    {
      "displayName": "VirtualNetworks",
      "name": "VirtualNetworks",
      "operations": [
        {
          "description": "Deletes virtual networks resource",
          "displayName": "Deletes virtual networks resource",
          "isDataAction": false,
          "name": "Microsoft.AzureStackHCI/VirtualNetworks/Delete",
          "origin": null,
          "properties": null
        },
        {
          "description": "Creates/Updates virtual networks resource",
          "displayName": "Creates/Updates virtual networks resource",
          "isDataAction": false,
          "name": "Microsoft.AzureStackHCI/VirtualNetworks/Write",
          "origin": null,
          "properties": null
        },
        {
          "description": "Gets/Lists virtual networks resource",
          "displayName": "Gets/Lists virtual networks resource",
          "isDataAction": false,
          "name": "Microsoft.AzureStackHCI/VirtualNetworks/Read",
          "origin": null,
          "properties": null
        }
      ]
    },
    {
      "displayName": "VirtualHardDisks",
      "name": "VirtualHardDisks",
      "operations": [
        {
          "description": "Deletes virtual hard disk resource",
          "displayName": "Deletes virtual hard disk resource",
          "isDataAction": false,
          "name": "Microsoft.AzureStackHCI/VirtualHardDisks/Delete",
          "origin": null,
          "properties": null
        },
        {
          "description": "Creates/Updates virtual hard disk resource",
          "displayName": "Creates/Updates virtual hard disk resource",
          "isDataAction": false,
          "name": "Microsoft.AzureStackHCI/VirtualHardDisks/Write",
          "origin": null,
          "properties": null
        },
        {
          "description": "Gets/Lists virtual hard disk resource",
          "displayName": "Gets/Lists virtual hard disk resource",
          "isDataAction": false,
          "name": "Microsoft.AzureStackHCI/VirtualHardDisks/Read",
          "origin": null,
          "properties": null
        }
      ]
    },
    {
      "displayName": "NetworkInterfaces",
      "name": "NetworkInterfaces",
      "operations": [
        {
          "description": "Deletes network interfaces resource",
          "displayName": "Deletes network interfaces resource",
          "isDataAction": false,
          "name": "Microsoft.AzureStackHCI/NetworkInterfaces/Delete",
          "origin": null,
          "properties": null
        },
        {
          "description": "Creates/Updates network interfaces resource",
          "displayName": "Creates/Updates network interfaces resource",
          "isDataAction": false,
          "name": "Microsoft.AzureStackHCI/NetworkInterfaces/Write",
          "origin": null,
          "properties": null
        },
        {
          "description": "Gets/Lists network interfaces resource",
          "displayName": "Gets/Lists network interfaces resource",
          "isDataAction": false,
          "name": "Microsoft.AzureStackHCI/NetworkInterfaces/Read",
          "origin": null,
          "properties": null
        }
      ]
    },
    {
      "displayName": "GalleryImages",
      "name": "GalleryImages",
      "operations": [
        {
          "description": "Deletes gallery images resource",
          "displayName": "Deletes gallery images resource",
          "isDataAction": false,
          "name": "Microsoft.AzureStackHCI/GalleryImages/Delete",
          "origin": null,
          "properties": null
        },
        {
          "description": "Creates/Updates gallery images resource",
          "displayName": "Creates/Updates gallery images resource",
          "isDataAction": false,
          "name": "Microsoft.AzureStackHCI/GalleryImages/Write",
          "origin": null,
          "properties": null
        },
        {
          "description": "Gets/Lists gallery images resource",
          "displayName": "Gets/Lists gallery images resource",
          "isDataAction": false,
          "name": "Microsoft.AzureStackHCI/GalleryImages/Read",
          "origin": null,
          "properties": null
        }
      ]
    },
    {
      "displayName": "VirtualMachines/HybridIdentityMetadata",
      "name": "VirtualMachines/HybridIdentityMetadata",
      "operations": [
        {
          "description": "Gets/Lists virtual machine hybrid identity metadata proxy resource",
          "displayName": "Gets/Lists virtual machine hybrid identity metadata proxy resource",
          "isDataAction": false,
          "name": "Microsoft.AzureStackHCI/VirtualMachines/HybridIdentityMetadata/Read",
          "origin": null,
          "properties": null
        }
      ]
    },
    {
      "displayName": "VirtualMachines/Extensions",
      "name": "VirtualMachines/Extensions",
      "operations": [
        {
          "description": "Gets/Lists virtual machine extensions resource",
          "displayName": "Gets/Lists virtual machine extensions resource",
          "isDataAction": false,
          "name": "Microsoft.AzureStackHCI/VirtualMachines/Extensions/Read",
          "origin": null,
          "properties": null
        },
        {
          "description": "Creates/Updates virtual machine extensions resource",
          "displayName": "Creates/Updates virtual machine extensions resource",
          "isDataAction": false,
          "name": "Microsoft.AzureStackHCI/VirtualMachines/Extensions/Write",
          "origin": null,
          "properties": null
        },
        {
          "description": "Deletes virtual machine extensions resource",
          "displayName": "Deletes virtual machine extensions resource",
          "isDataAction": false,
          "name": "Microsoft.AzureStackHCI/VirtualMachines/Extensions/Delete",
          "origin": null,
          "properties": null
        }
      ]
    },
    {
      "displayName": "StorageContainers",
      "name": "StorageContainers",
      "operations": [
        {
          "description": "Deletes storage containers resource",
          "displayName": "Deletes storage containers resource",
          "isDataAction": false,
          "name": "Microsoft.AzureStackHCI/StorageContainers/Delete",
          "origin": null,
          "properties": null
        },
        {
          "description": "Creates/Updates storage containers resource",
          "displayName": "Creates/Updates storage containers resource",
          "isDataAction": false,
          "name": "Microsoft.AzureStackHCI/StorageContainers/Write",
          "origin": null,
          "properties": null
        },
        {
          "description": "Gets/Lists storage containers resource",
          "displayName": "Gets/Lists storage containers resource",
          "isDataAction": false,
          "name": "Microsoft.AzureStackHCI/StorageContainers/Read",
          "origin": null,
          "properties": null
        }
      ]
    },
    {
      "displayName": "MarketPlaceGalleryImages",
      "name": "MarketPlaceGalleryImages",
      "operations": [
        {
          "description": "Deletes market place gallery images resource",
          "displayName": "Deletes market place gallery images resource",
          "isDataAction": false,
          "name": "Microsoft.AzureStackHCI/MarketPlaceGalleryImages/Delete",
          "origin": null,
          "properties": null
        },
        {
          "description": "Creates/Updates market place gallery images resource",
          "displayName": "Creates/Updates market place gallery images resource",
          "isDataAction": false,
          "name": "Microsoft.AzureStackHCI/MarketPlaceGalleryImages/Write",
          "origin": null,
          "properties": null
        },
        {
          "description": "Gets/Lists market place gallery images resource",
          "displayName": "Gets/Lists market place gallery images resource",
          "isDataAction": false,
          "name": "Microsoft.AzureStackHCI/MarketPlaceGalleryImages/Read",
          "origin": null,
          "properties": null
        }
      ]
    },
    {
      "displayName": "RegisteredSubscriptions",
      "name": "RegisteredSubscriptions",
      "operations": [
        {
          "description": "Reads registered subscriptions",
          "displayName": "Gets/Lists registered subscriptions",
          "isDataAction": false,
          "name": "Microsoft.AzureStackHCI/RegisteredSubscriptions/read",
          "origin": null,
          "properties": null
        }
      ]
    }
  ],
  "type": "Microsoft.Authorization/providerOperations"
}
