{
  "assignableScopes": [
    "/"
  ],
  "createdBy": null,
  "createdOn": "2019-10-25T18:41:40.118506+00:00",
  "description": "Allows full access to App Configuration data.",
  "id": "/providers/Microsoft.Authorization/roleDefinitions/5ae67dd6-50cb-40e7-96ff-dc2bfa4b606b",
  "name": "5ae67dd6-50cb-40e7-96ff-dc2bfa4b606b",
  "permissions": [
    {
      "actions": [],
      "condition": null,
      "conditionVersion": null,
      "dataActions": [
        "Microsoft.AppConfiguration/configurationStores/*/read",
        "Microsoft.AppConfiguration/configurationStores/*/write",
        "Microsoft.AppConfiguration/configurationStores/*/delete",
        "Microsoft.AppConfiguration/configurationStores/*/action"
      ],
      "notActions": [],
      "notDataActions": []
    }
  ],
  "roleName": "App Configuration Data Owner",
  "roleType": "BuiltInRole",
  "type": "Microsoft.Authorization/roleDefinitions",
  "updatedBy": null,
  "updatedOn": "2023-02-03T23:50:20.568709+00:00"
}
