{
  "assignableScopes": [
    "/"
  ],
  "createdBy": null,
  "createdOn": "2023-10-30T19:09:08.804129+00:00",
  "description": "Can perform all actions required to create a resource deployment within a resource group.",
  "id": "/providers/Microsoft.Authorization/roleDefinitions/3afb7f49-54cb-416e-8c09-6dc049efa503",
  "name": "3afb7f49-54cb-416e-8c09-6dc049efa503",
  "permissions": [
    {
      "actions": [
        "Microsoft.Authorization/*/read",
        "Microsoft.Resources/deployments/*",
        "Microsoft.Insights/AutoscaleSettings/write"
      ],
      "condition": null,
      "conditionVersion": null,
      "dataActions": [],
      "notActions": [],
      "notDataActions": []
    }
  ],
  "roleName": "Azure AI Inference Deployment Operator",
  "roleType": "BuiltInRole",
  "type": "Microsoft.Authorization/roleDefinitions",
  "updatedBy": null,
  "updatedOn": "2024-03-19T15:23:15.413852+00:00"
}
