{
  "assignableScopes": [
    "/"
  ],
  "description": "Can manage blueprint definitions, but not assign them.",
  "id": "/providers/Microsoft.Authorization/roleDefinitions/41077137-e803-4205-871c-5a86e6a753b4",
  "name": "41077137-e803-4205-871c-5a86e6a753b4",
  "permissions": [
    {
      "actions": [
        "Microsoft.Authorization/*/read",
        "Microsoft.Blueprint/blueprints/*",
        "Microsoft.Resources/subscriptions/resourceGroups/read",
        "Microsoft.Resources/deployments/*",
        "Microsoft.Support/*"
      ],
      "dataActions": [],
      "notActions": [],
      "notDataActions": []
    }
  ],
  "roleName": "Blueprint Contributor",
  "roleType": "BuiltInRole",
  "type": "Microsoft.Authorization/roleDefinitions"
}
