{
  "assignableScopes": [
    "/"
  ],
  "createdBy": null,
  "createdOn": "2024-02-27T16:09:02.834677+00:00",
  "description": "View GeoCatalogs, but does not allow you to make any changes.",
  "id": "/providers/Microsoft.Authorization/roleDefinitions/b7b8f583-43d0-40ae-b147-6b46f53661c1",
  "name": "b7b8f583-43d0-40ae-b147-6b46f53661c1",
  "permissions": [
    {
      "actions": [
        "Microsoft.Authorization/*/read",
        "Microsoft.Insights/alertRules/*",
        "Microsoft.Resources/deployments/*",
        "Microsoft.Resources/subscriptions/resourceGroups/read",
        "Microsoft.Orbital/operations/read",
        "Microsoft.Orbital/geoCatalogs/read"
      ],
      "condition": null,
      "conditionVersion": null,
      "dataActions": [],
      "notActions": [],
      "notDataActions": []
    }
  ],
  "roleName": "GeoCatalog Reader",
  "roleType": "BuiltInRole",
  "type": "Microsoft.Authorization/roleDefinitions",
  "updatedBy": null,
  "updatedOn": "2024-02-27T16:09:02.834677+00:00"
}
