{
  "assignableScopes": [
    "/"
  ],
  "createdBy": null,
  "createdOn": "2024-05-14T15:16:27.709987+00:00",
  "description": "Read-write access to Nexus Network Fabric Service",
  "id": "/providers/Microsoft.Authorization/roleDefinitions/a5eb8433-97a5-4a06-80b2-a877e1622c31",
  "name": "a5eb8433-97a5-4a06-80b2-a877e1622c31",
  "permissions": [
    {
      "actions": [
        "Microsoft.ManagedNetworkFabric/*/read",
        "Microsoft.ManagedNetworkFabric/*/write",
        "Microsoft.Authorization/*/read",
        "Microsoft.Insights/alertRules/*",
        "Microsoft.Resources/deployments/*",
        "Microsoft.Resources/subscriptions/resourceGroups/read"
      ],
      "condition": null,
      "conditionVersion": null,
      "dataActions": [],
      "notActions": [],
      "notDataActions": []
    }
  ],
  "roleName": "Nexus Network Fabric Service Writer",
  "roleType": "BuiltInRole",
  "type": "Microsoft.Authorization/roleDefinitions",
  "updatedBy": null,
  "updatedOn": "2024-05-14T15:16:27.709987+00:00"
}
