{
  "assignableScopes": [
    "/"
  ],
  "description": "Lets you manage Traffic Manager profiles, but does not let you control who has access to them.",
  "id": "/providers/Microsoft.Authorization/roleDefinitions/a4b10055-b0c7-44c2-b00f-c7b5b3550cf7",
  "name": "a4b10055-b0c7-44c2-b00f-c7b5b3550cf7",
  "permissions": [
    {
      "actions": [
        "Microsoft.Authorization/*/read",
        "Microsoft.Insights/alertRules/*",
        "Microsoft.Network/trafficManagerProfiles/*",
        "Microsoft.ResourceHealth/availabilityStatuses/read",
        "Microsoft.Resources/deployments/*",
        "Microsoft.Resources/subscriptions/resourceGroups/read",
        "Microsoft.Support/*"
      ],
      "dataActions": [],
      "notActions": [],
      "notDataActions": []
    }
  ],
  "roleName": "Traffic Manager Contributor",
  "roleType": "BuiltInRole",
  "type": "Microsoft.Authorization/roleDefinitions"
}
